LICENSE
MANIFEST.in
README.rst
setup.py
django_zotero/__init__.py
django_zotero/admin.py
django_zotero/forms.py
django_zotero/models.py
django_zotero/signals.py
django_zotero/tests.py
django_zotero/urls.py
django_zotero/utils.py
django_zotero/views.py
django_zotero.egg-info/PKG-INFO
django_zotero.egg-info/SOURCES.txt
django_zotero.egg-info/dependency_links.txt
django_zotero.egg-info/not-zip-safe
django_zotero.egg-info/pbr.json
django_zotero.egg-info/requires.txt
django_zotero.egg-info/top_level.txt
django_zotero/fixtures/initial_data.json
django_zotero/media/valid_zotero_itemtypes_and_fields.txt
django_zotero/static/css/tags.css
django_zotero/static/img/delete.png
django_zotero/static/img/icon_alert.gif
django_zotero/static/js/jquery-1.4.2.js
django_zotero/static/js/jquery.formset.js
django_zotero/static/js/jquery.js
django_zotero/static/js/tags.js
django_zotero/static/js/tags_admin.js
django_zotero/templates/admin/base_site.html
django_zotero/templates/admin/edit_inline/extended_tabular.html
django_zotero/templates/zotero/inline_tags.html
django_zotero/templates/zotero/document/detail.html
django_zotero/templates/zotero/document/index.html
django_zotero/templatetags/__init__.py
django_zotero/templatetags/__init__.pyc
django_zotero/templatetags/zotero_inline_extras.py
django_zotero/templatetags/zotero_inline_extras.pyc
django_zotero/templatetags/zotero_tags_extras.py
django_zotero/templatetags/zotero_tags_extras.pyc