Metadata-Version: 1.1
Name: django-zotero
Version: 0.4
Summary: Django tool to tag objects and export them to Zotero
Home-page: https://github.com/CulturePlex/django-zotero
Author: Antonio Jimenez Mavillard
Author-email: ajmavillard@gmail.com
License: MIT
Keywords: zotero django admin tag meta metatag
Platform: UNKNOWN
Classifier: Development Status :: 4 - Beta
Classifier: Framework :: Django
Classifier: Intended Audience :: Developers
Classifier: License :: OSI Approved :: MIT License
Classifier: Operating System :: OS Independent
Classifier: Programming Language :: JavaScript
Classifier: Programming Language :: Python
Classifier: Topic :: Internet :: WWW/HTTP
